flake8_picky_parentheses/__init__.py
flake8_picky_parentheses/_brackets_position.py
flake8_picky_parentheses/_meta.py
flake8_picky_parentheses/_redundant_parentheses.py
flake8_picky_parentheses/_util.py
flake8_picky_parentheses-0.6.1.dist-info/licenses/LICENSE
flake8_picky_parentheses-0.6.1.dist-info/METADATA
flake8_picky_parentheses-0.6.1.dist-info/WHEEL
flake8_picky_parentheses-0.6.1.dist-info/entry_points.txt
flake8_picky_parentheses-0.6.1.dist-info/top_level.txt
flake8_picky_parentheses-0.6.1.dist-info/RECORD
