Metadata-Version: 2.4
Name: flake8-picky-parentheses
Version: 0.6.1
Summary: flake8 plugin to nitpick about parenthesis, brackets, and braces
Author: Ivan Prychantovskyi, Rouven Bauer
License: Apache License 2.0
Project-URL: Homepage, https://github.com/robsdedude/flake8-picky-parentheses
Project-URL: Issue Tracker, https://github.com/robsdedude/flake8-picky-parentheses/issues
Project-URL: Source Code, https://github.com/robsdedude/flake8-picky-parentheses
Project-URL: Changelog, https://github.com/robsdedude/flake8-picky-parentheses/blob/master/CHANGELOG.md
Keywords: flake8,plugin,redundant,superfluous,extraneous,unnecessary,parentheses,parenthesis,parens,brackets,linter,linting,codestyle,code style
Classifier: Framework :: Flake8
Classifier: Environment :: Console
Classifier: Intended Audience :: Developers
Classifier: License :: OSI Approved :: Apache Software License
Classifier: Programming Language :: Python
Classifier: Programming Language :: Python :: 3
Classifier: Programming Language :: Python :: 3.7
Classifier: Programming Language :: Python :: 3.8
Classifier: Programming Language :: Python :: 3.9
Classifier: Programming Language :: Python :: 3.10
Classifier: Programming Language :: Python :: 3.11
Classifier: Programming Language :: Python :: 3.12
Classifier: Programming Language :: Python :: 3.13
Classifier: Programming Language :: Python :: 3.14
Classifier: Topic :: Software Development :: Libraries :: Python Modules
Classifier: Topic :: Software Development :: Quality Assurance
Requires-Python: >=3.7
License-File: LICENSE
Requires-Dist: flake8<8.0,>=3.7
Dynamic: license-file
